[
 {
  "docstatus": 0,
  "doctype": "Workflow",
  "document_type": "Payment Entry",
  "is_active": 1,
  "modified": "2024-07-29 10:53:50.991263",
  "name": "Payment Request",
  "override_status": 0,
  "send_email_alert": 0,
  "states": [
   {
    "allow_edit": "All",
    "avoid_status_override": 0,
    "doc_status": "0",
    "is_optional_state": 0,
    "message": null,
    "next_action_email_template": null,
    "parent": "Payment Request",
    "parentfield": "states",
    "parenttype": "Workflow",
    "state": "Draft",
    "update_field": null,
    "update_value": null,
    "workflow_builder_id": null
   },
   {
    "allow_edit": "Senior Accountant",
    "avoid_status_override": 0,
    "doc_status": "0",
    "is_optional_state": 0,
    "message": null,
    "next_action_email_template": null,
    "parent": "Payment Request",
    "parentfield": "states",
    "parenttype": "Workflow",
    "state": "Verified by Senior Accountant",
    "update_field": null,
    "update_value": null,
    "workflow_builder_id": null
   },
   {
    "allow_edit": "Lead Accountant",
    "avoid_status_override": 0,
    "doc_status": "0",
    "is_optional_state": 0,
    "message": null,
    "next_action_email_template": null,
    "parent": "Payment Request",
    "parentfield": "states",
    "parenttype": "Workflow",
    "state": "Approved by Lead Accountant",
    "update_field": null,
    "update_value": null,
    "workflow_builder_id": null
   },
   {
    "allow_edit": "Finance Director",
    "avoid_status_override": 0,
    "doc_status": "0",
    "is_optional_state": 0,
    "message": null,
    "next_action_email_template": null,
    "parent": "Payment Request",
    "parentfield": "states",
    "parenttype": "Workflow",
    "state": "Recommended by Finance Director",
    "update_field": null,
    "update_value": null,
    "workflow_builder_id": null
   },
   {
    "allow_edit": "Senior Accountant",
    "avoid_status_override": 0,
    "doc_status": "1",
    "is_optional_state": 0,
    "message": null,
    "next_action_email_template": null,
    "parent": "Payment Request",
    "parentfield": "states",
    "parenttype": "Workflow",
    "state": "Completed",
    "update_field": null,
    "update_value": null,
    "workflow_builder_id": null
   },
   {
    "allow_edit": "All",
    "avoid_status_override": 0,
    "doc_status": "0",
    "is_optional_state": 0,
    "message": null,
    "next_action_email_template": null,
    "parent": "Payment Request",
    "parentfield": "states",
    "parenttype": "Workflow",
    "state": "Rejected",
    "update_field": null,
    "update_value": null,
    "workflow_builder_id": null
   }
  ],
  "transitions": [
   {
    "action": "Approve",
    "allow_self_approval": 1,
    "allowed": "Senior Accountant",
    "condition": "doc.payment_type == \"Pay\"",
    "next_state": "Verified by Senior Accountant",
    "parent": "Payment Request",
    "parentfield": "transitions",
    "parenttype": "Workflow",
    "state": "Draft",
    "workflow_builder_id": null
   },
   {
    "action": "Submit",
    "allow_self_approval": 1,
    "allowed": "All",
    "condition": "doc.payment_type != \"Pay\"",
    "next_state": "Completed",
    "parent": "Payment Request",
    "parentfield": "transitions",
    "parenttype": "Workflow",
    "state": "Draft",
    "workflow_builder_id": null
   },
   {
    "action": "Approve",
    "allow_self_approval": 1,
    "allowed": "Lead Accountant",
    "condition": null,
    "next_state": "Approved by Lead Accountant",
    "parent": "Payment Request",
    "parentfield": "transitions",
    "parenttype": "Workflow",
    "state": "Verified by Senior Accountant",
    "workflow_builder_id": null
   },
   {
    "action": "Reject",
    "allow_self_approval": 1,
    "allowed": "Lead Accountant",
    "condition": null,
    "next_state": "Rejected",
    "parent": "Payment Request",
    "parentfield": "transitions",
    "parenttype": "Workflow",
    "state": "Verified by Senior Accountant",
    "workflow_builder_id": null
   },
   {
    "action": "Return to Initiator",
    "allow_self_approval": 1,
    "allowed": "Lead Accountant",
    "condition": null,
    "next_state": "Draft",
    "parent": "Payment Request",
    "parentfield": "transitions",
    "parenttype": "Workflow",
    "state": "Verified by Senior Accountant",
    "workflow_builder_id": null
   },
   {
    "action": "Approve",
    "allow_self_approval": 1,
    "allowed": "Finance Director",
    "condition": null,
    "next_state": "Recommended by Finance Director",
    "parent": "Payment Request",
    "parentfield": "transitions",
    "parenttype": "Workflow",
    "state": "Approved by Lead Accountant",
    "workflow_builder_id": null
   },
   {
    "action": "Reject",
    "allow_self_approval": 1,
    "allowed": "Finance Director",
    "condition": null,
    "next_state": "Rejected",
    "parent": "Payment Request",
    "parentfield": "transitions",
    "parenttype": "Workflow",
    "state": "Approved by Lead Accountant",
    "workflow_builder_id": null
   },
   {
    "action": "Return to Senior Accountant",
    "allow_self_approval": 1,
    "allowed": "Finance Director",
    "condition": null,
    "next_state": "Verified by Senior Accountant",
    "parent": "Payment Request",
    "parentfield": "transitions",
    "parenttype": "Workflow",
    "state": "Approved by Lead Accountant",
    "workflow_builder_id": null
   },
   {
    "action": "Approve",
    "allow_self_approval": 1,
    "allowed": "Senior Accountant",
    "condition": null,
    "next_state": "Completed",
    "parent": "Payment Request",
    "parentfield": "transitions",
    "parenttype": "Workflow",
    "state": "Recommended by Finance Director",
    "workflow_builder_id": null
   }
  ],
  "workflow_data": null,
  "workflow_name": "Payment Request",
  "workflow_state_field": "workflow_state"
 }
]